{
"type": "FeatureCollection",
"crs": { "type": "name", "properties": { "name": "urn:ogc:def:crs:OGC:1.3:CRS84" } },
"features": [
{ "type": "Feature", "properties": { "gid": 246, "rotation": -42, "name": "DE01-DE02" }, "geometry": { "type": "Point", "coordinates": [ 7.61, 53.78 ] } }
]
}
